ex4/add4.v
module  add4( sum, co, a, b, ci);

  input   [3:0] a, b;
  input   ci;
  output  [3:0] sum;
  output  co;

  assign {co, sum} = a + b + ci;  
endmodule

ex5/addsub.v
`include "../ex4/add4.v"
module	addsub( result, operand_a, operand_b, mode );

	input	[3:0]	operand_a, operand_b;
	input	mode;
	output	[3:0]	result;
	wire co;
	wire	[3:0]	xor_b;

	xor	g0(xor_b[0],operand_b[0],mode);
	xor	g1(xor_b[1],operand_b[1],mode);
	xor	g2(xor_b[2],operand_b[2],mode);
	xor	g3(xor_b[3],operand_b[3],mode);
	
	add4	m1(
		.sum(result),
		.co(co),
		.a(operand_a),	 
		.b(xor_b),	
		.ci(mode)
	);	
endmodule

ex5/addsub_tb.v
module	addsub_tb;
	
	// for DUT port connection
	reg					mode;
	reg 	[3:0]	operand_a, operand_b;
	wire	[3:0] result;
	wire co;
	
	// for pattern generation
	integer			a, b, expect, error_num, t;
	reg					overflow;
	wire	[3:0]	expect_out = expect[3:0];	// compare "expect_out" with "result"

	addsub addsub( result, operand_a, operand_b, mode );
	assign co = overflow; //overflow parameter is carry bit
	
	// give stimulus pattern
	initial begin
	error_num = 0;

	$dumpfile("waves.vcd");
	$dumpvars;

	$display( "\nTest subtraction mode." );
	#10 mode = 1'b1;
	
	for( a=-8; a<=7; a=a+1 ) begin
		for( b=-8; b<=7; b=b+1 ) begin
			
			operand_a = a[3:0];
			operand_b = b[3:0];
			expect = a - b;
	
			#1;
			if( expect >= -8 && expect <= 7 ) begin
				overflow = 1'b0;
				if( expect[3:0] !== result ) begin
					error_num = error_num + 1;
					$display( "Error(%d):(%d)-(%d) Expect(%b) Output(%b)", error_num[9:0], a, b, expect[3:0], result );
				end
			end	else begin
				overflow = 1'b1;
			end
	
			#1;
		end
	end

	$display( "\nTest addition mode." );
	mode = 1'b0;
	
	for( a=-8; a<=7; a=a+1 ) begin
		for( b=-8; b<=7; b=b+1 ) begin
			
			operand_a = a[3:0];
			operand_b = b[3:0];
			expect = a + b;
	
			#1;
			if( expect >= -8 && expect <= 7 ) begin
				overflow = 1'b0;
				if( expect[3:0] !== result ) begin
					error_num = error_num + 1;
					$display( "Error(%d):(%d)+(%d) Expect(%b) Output(%b)", error_num[9:0], a, b, expect[3:0], result );
				end
			end	else begin
				overflow = 1'b1;
			end
	
			#1;
		end
	end
	
	if( error_num==0 )
		$display( "\nPass all test\n" );
	else
		$display( "\nFail, error number = %d\n", error_num );
	
	#10 $finish;
	end

endmodule

ex5/waves.vcd
$date
    Nov 11, 2021  16:34:50
$end
$version
    TOOL:	ncsim(64)	15.20-s085
$end
$timescale
    1 ns
$end

$scope module addsub_tb $end
$var reg       1 !    mode  $end
$var reg       4 "    operand_a [3:0] $end
$var reg       4 #    operand_b [3:0] $end
$var wire      4 $    result [3:0] $end
$var wire      1 %    co  $end
$var integer  32 &    a  $end
$var integer  32 '    b  $end
$var integer  32 (    expect  $end
$var integer  32 )    error_num  $end
$var integer  32 *    t  $end
$var reg       1 +    overflow  $end
$var wire      4 ,    expect_out [3:0] $end

$scope module addsub $end
$var wire      4 -    operand_a [3:0] $end
$var wire      1 .    operand_b [3] $end
$var wire      1 /    operand_b [2] $end
$var wire      1 0    operand_b [1] $end
$var wire      1 1    operand_b [0] $end
$var wire      1 2    mode  $end
$var wire      4 $    result [3:0] $end
$var wire      1 3    co  $end
$var wire      1 4    xor_b [3] $end
$var wire      1 5    xor_b [2] $end
$var wire      1 6    xor_b [1] $end
$var wire      1 7    xor_b [0] $end

$scope module m1 $end
$var wire      4 -    a [3:0] $end
$var wire      1 4    b [3] $end
$var wire      1 5    b [2] $end
$var wire      1 6    b [1] $end
$var wire      1 7    b [0] $end
$var wire      1 2    ci  $end
$var wire      4 $    sum [3:0] $end
$var wire      1 3    co  $end
$upscope $end

$upscope $end

$upscope $end

$enddefinitions $end
$dumpvars
x!
bx "
bx #
bx $
x%
bx &
bx '
bx (
b0 )
bx *
x+
bx ,
bx -
x.
x/
x0
x1
x2
x3
x4
x5
x6
x7
$end
#10
1!
b11111111111111111111111111111000 &
b11111111111111111111111111111000 '
b1000 "
b1000 #
b0 (
b0 ,
1.
0/
00
01
b1000 -
12
04
15
16
17
13
b0 $
#11
0+
0%
#12
b11111111111111111111111111111001 '
b1001 #
b11111111111111111111111111111111 (
b1111 ,
11
07
03
b1111 $
#14
b11111111111111111111111111111010 '
b1010 #
b11111111111111111111111111111110 (
b1110 ,
10
01
17
06
b1110 $
#16
b11111111111111111111111111111011 '
b1011 #
b11111111111111111111111111111101 (
b1101 ,
11
07
b1101 $
#18
b11111111111111111111111111111100 '
b1100 #
b11111111111111111111111111111100 (
b1100 ,
1/
00
01
17
16
05
b1100 $
#20
b11111111111111111111111111111101 '
b1101 #
b11111111111111111111111111111011 (
b1011 ,
11
07
b1011 $
#22
b11111111111111111111111111111110 '
b1110 #
b11111111111111111111111111111010 (
b1010 ,
10
01
17
06
b1010 $
#24
b11111111111111111111111111111111 '
b1111 #
b11111111111111111111111111111001 (
b1001 ,
11
07
b1001 $
#26
b0 '
b0 #
b11111111111111111111111111111000 (
b1000 ,
0.
0/
00
01
17
16
15
14
13
b1000 $
#28
b1 '
b1 #
b11111111111111111111111111110111 (
b111 ,
11
07
b111 $
#29
1+
1%
#30
b10 '
b10 #
b11111111111111111111111111110110 (
b110 ,
10
01
17
06
b110 $
#32
b11 '
b11 #
b11111111111111111111111111110101 (
b101 ,
11
07
b101 $
#34
b100 '
b100 #
b11111111111111111111111111110100 (
b100 ,
1/
00
01
17
16
05
b100 $
#36
b101 '
b101 #
b11111111111111111111111111110011 (
b11 ,
11
07
b11 $
#38
b110 '
b110 #
b11111111111111111111111111110010 (
b10 ,
10
01
17
06
b10 $
#40
b111 '
b111 #
b11111111111111111111111111110001 (
b1 ,
11
07
b1 $
#42
b1000 '
b11111111111111111111111111111001 &
b11111111111111111111111111111000 '
b1001 "
b1000 #
b1 (
1.
0/
00
01
b1001 -
17
16
15
04
#43
0+
0%
#44
b11111111111111111111111111111001 '
b1001 #
b0 (
b0 ,
11
07
b0 $
#46
b11111111111111111111111111111010 '
b1010 #
b11111111111111111111111111111111 (
b1111 ,
10
01
17
06
03
b1111 $
#48
b11111111111111111111111111111011 '
b1011 #
b11111111111111111111111111111110 (
b1110 ,
11
07
b1110 $
#50
b11111111111111111111111111111100 '
b1100 #
b11111111111111111111111111111101 (
b1101 ,
1/
00
01
17
16
05
b1101 $
#52
b11111111111111111111111111111101 '
b1101 #
b11111111111111111111111111111100 (
b1100 ,
11
07
b1100 $
#54
b11111111111111111111111111111110 '
b1110 #
b11111111111111111111111111111011 (
b1011 ,
10
01
17
06
b1011 $
#56
b11111111111111111111111111111111 '
b1111 #
b11111111111111111111111111111010 (
b1010 ,
11
07
b1010 $
#58
b0 '
b0 #
b11111111111111111111111111111001 (
b1001 ,
0.
0/
00
01
17
16
15
14
13
b1001 $
#60
b1 '
b1 #
b11111111111111111111111111111000 (
b1000 ,
11
07
b1000 $
#62
b10 '
b10 #
b11111111111111111111111111110111 (
b111 ,
10
01
17
06
b111 $
#63
1+
1%
#64
b11 '
b11 #
b11111111111111111111111111110110 (
b110 ,
11
07
b110 $
#66
b100 '
b100 #
b11111111111111111111111111110101 (
b101 ,
1/
00
01
17
16
05
b101 $
#68
b101 '
b101 #
b11111111111111111111111111110100 (
b100 ,
11
07
b100 $
#70
b110 '
b110 #
b11111111111111111111111111110011 (
b11 ,
10
01
17
06
b11 $
#72
b111 '
b111 #
b11111111111111111111111111110010 (
b10 ,
11
07
b10 $
#74
b1000 '
b11111111111111111111111111111010 &
b11111111111111111111111111111000 '
b1010 "
b1000 #
b10 (
1.
0/
00
01
b1010 -
17
16
15
04
#75
0+
0%
#76
b11111111111111111111111111111001 '
b1001 #
b1 (
b1 ,
11
07
b1 $
#78
b11111111111111111111111111111010 '
b1010 #
b0 (
b0 ,
10
01
17
06
b0 $
#80
b11111111111111111111111111111011 '
b1011 #
b11111111111111111111111111111111 (
b1111 ,
11
07
03
b1111 $
#82
b11111111111111111111111111111100 '
b1100 #
b11111111111111111111111111111110 (
b1110 ,
1/
00
01
17
16
05
b1110 $
#84
b11111111111111111111111111111101 '
b1101 #
b11111111111111111111111111111101 (
b1101 ,
11
07
b1101 $
#86
b11111111111111111111111111111110 '
b1110 #
b11111111111111111111111111111100 (
b1100 ,
10
01
17
06
b1100 $
#88
b11111111111111111111111111111111 '
b1111 #
b11111111111111111111111111111011 (
b1011 ,
11
07
b1011 $
#90
b0 '
b0 #
b11111111111111111111111111111010 (
b1010 ,
0.
0/
00
01
17
16
15
14
13
b1010 $
#92
b1 '
b1 #
b11111111111111111111111111111001 (
b1001 ,
11
07
b1001 $
#94
b10 '
b10 #
b11111111111111111111111111111000 (
b1000 ,
10
01
17
06
b1000 $
#96
b11 '
b11 #
b11111111111111111111111111110111 (
b111 ,
11
07
b111 $
#97
1+
1%
#98
b100 '
b100 #
b11111111111111111111111111110110 (
b110 ,
1/
00
01
17
16
05
b110 $
#100
b101 '
b101 #
b11111111111111111111111111110101 (
b101 ,
11
07
b101 $
#102
b110 '
b110 #
b11111111111111111111111111110100 (
b100 ,
10
01
17
06
b100 $
#104
b111 '
b111 #
b11111111111111111111111111110011 (
b11 ,
11
07
b11 $
#106
b1000 '
b11111111111111111111111111111011 &
b11111111111111111111111111111000 '
b1011 "
b1000 #
b11 (
1.
0/
00
01
b1011 -
17
16
15
04
#107
0+
0%
#108
b11111111111111111111111111111001 '
b1001 #
b10 (
b10 ,
11
07
b10 $
#110
b11111111111111111111111111111010 '
b1010 #
b1 (
b1 ,
10
01
17
06
b1 $
#112
b11111111111111111111111111111011 '
b1011 #
b0 (
b0 ,
11
07
b0 $
#114
b11111111111111111111111111111100 '
b1100 #
b11111111111111111111111111111111 (
b1111 ,
1/
00
01
17
16
05
03
b1111 $
#116
b11111111111111111111111111111101 '
b1101 #
b11111111111111111111111111111110 (
b1110 ,
11
07
b1110 $
#118
b11111111111111111111111111111110 '
b1110 #
b11111111111111111111111111111101 (
b1101 ,
10
01
17
06
b1101 $
#120
b11111111111111111111111111111111 '
b1111 #
b11111111111111111111111111111100 (
b1100 ,
11
07
b1100 $
#122
b0 '
b0 #
b11111111111111111111111111111011 (
b1011 ,
0.
0/
00
01
17
16
15
14
13
b1011 $
#124
b1 '
b1 #
b11111111111111111111111111111010 (
b1010 ,
11
07
b1010 $
#126
b10 '
b10 #
b11111111111111111111111111111001 (
b1001 ,
10
01
17
06
b1001 $
#128
b11 '
b11 #
b11111111111111111111111111111000 (
b1000 ,
11
07
b1000 $
#130
b100 '
b100 #
b11111111111111111111111111110111 (
b111 ,
1/
00
01
17
16
05
b111 $
#131
1+
1%
#132
b101 '
b101 #
b11111111111111111111111111110110 (
b110 ,
11
07
b110 $
#134
b110 '
b110 #
b11111111111111111111111111110101 (
b101 ,
10
01
17
06
b101 $
#136
b111 '
b111 #
b11111111111111111111111111110100 (
b100 ,
11
07
b100 $
#138
b1000 '
b11111111111111111111111111111100 &
b11111111111111111111111111111000 '
b1100 "
b1000 #
b100 (
1.
0/
00
01
b1100 -
17
16
15
04
#139
0+
0%
#140
b11111111111111111111111111111001 '
b1001 #
b11 (
b11 ,
11
07
b11 $
#142
b11111111111111111111111111111010 '
b1010 #
b10 (
b10 ,
10
01
17
06
b10 $
#144
b11111111111111111111111111111011 '
b1011 #
b1 (
b1 ,
11
07
b1 $
#146
b11111111111111111111111111111100 '
b1100 #
b0 (
b0 ,
1/
00
01
17
16
05
b0 $
#148
b11111111111111111111111111111101 '
b1101 #
b11111111111111111111111111111111 (
b1111 ,
11
07
03
b1111 $
#150
b11111111111111111111111111111110 '
b1110 #
b11111111111111111111111111111110 (
b1110 ,
10
01
17
06
b1110 $
#152
b11111111111111111111111111111111 '
b1111 #
b11111111111111111111111111111101 (
b1101 ,
11
07
b1101 $
#154
b0 '
b0 #
b11111111111111111111111111111100 (
b1100 ,
0.
0/
00
01
17
16
15
14
13
b1100 $
#156
b1 '
b1 #
b11111111111111111111111111111011 (
b1011 ,
11
07
b1011 $
#158
b10 '
b10 #
b11111111111111111111111111111010 (
b1010 ,
10
01
17
06
b1010 $
#160
b11 '
b11 #
b11111111111111111111111111111001 (
b1001 ,
11
07
b1001 $
#162
b100 '
b100 #
b11111111111111111111111111111000 (
b1000 ,
1/
00
01
17
16
05
b1000 $
#164
b101 '
b101 #
b11111111111111111111111111110111 (
b111 ,
11
07
b111 $
#165
1+
1%
#166
b110 '
b110 #
b11111111111111111111111111110110 (
b110 ,
10
01
17
06
b110 $
#168
b111 '
b111 #
b11111111111111111111111111110101 (
b101 ,
11
07
b101 $
#170
b1000 '
b11111111111111111111111111111101 &
b11111111111111111111111111111000 '
b1101 "
b1000 #
b101 (
1.
0/
00
01
b1101 -
17
16
15
04
#171
0+
0%
#172
b11111111111111111111111111111001 '
b1001 #
b100 (
b100 ,
11
07
b100 $
#174
b11111111111111111111111111111010 '
b1010 #
b11 (
b11 ,
10
01
17
06
b11 $
#176
b11111111111111111111111111111011 '
b1011 #
b10 (
b10 ,
11
07
b10 $
#178
b11111111111111111111111111111100 '
b1100 #
b1 (
b1 ,
1/
00
01
17
16
05
b1 $
#180
b11111111111111111111111111111101 '
b1101 #
b0 (
b0 ,
11
07
b0 $
#182
b11111111111111111111111111111110 '
b1110 #
b11111111111111111111111111111111 (
b1111 ,
10
01
17
06
03
b1111 $
#184
b11111111111111111111111111111111 '
b1111 #
b11111111111111111111111111111110 (
b1110 ,
11
07
b1110 $
#186
b0 '
b0 #
b11111111111111111111111111111101 (
b1101 ,
0.
0/
00
01
17
16
15
14
13
b1101 $
#188
b1 '
b1 #
b11111111111111111111111111111100 (
b1100 ,
11
07
b1100 $
#190
b10 '
b10 #
b11111111111111111111111111111011 (
b1011 ,
10
01
17
06
b1011 $
#192
b11 '
b11 #
b11111111111111111111111111111010 (
b1010 ,
11
07
b1010 $
#194
b100 '
b100 #
b11111111111111111111111111111001 (
b1001 ,
1/
00
01
17
16
05
b1001 $
#196
b101 '
b101 #
b11111111111111111111111111111000 (
b1000 ,
11
07
b1000 $
#198
b110 '
b110 #
b11111111111111111111111111110111 (
b111 ,
10
01
17
06
b111 $
#199
1+
1%
#200
b111 '
b111 #
b11111111111111111111111111110110 (
b110 ,
11
07
b110 $
#202
b1000 '
b11111111111111111111111111111110 &
b11111111111111111111111111111000 '
b1110 "
b1000 #
b110 (
1.
0/
00
01
b1110 -
17
16
15
04
#203
0+
0%
#204
b11111111111111111111111111111001 '
b1001 #
b101 (
b101 ,
11
07
b101 $
#206
b11111111111111111111111111111010 '
b1010 #
b100 (
b100 ,
10
01
17
06
b100 $
#208
b11111111111111111111111111111011 '
b1011 #
b11 (
b11 ,
11
07
b11 $
#210
b11111111111111111111111111111100 '
b1100 #
b10 (
b10 ,
1/
00
01
17
16
05
b10 $
#212
b11111111111111111111111111111101 '
b1101 #
b1 (
b1 ,
11
07
b1 $
#214
b11111111111111111111111111111110 '
b1110 #
b0 (
b0 ,
10
01
17
06
b0 $
#216
b11111111111111111111111111111111 '
b1111 #
b11111111111111111111111111111111 (
b1111 ,
11
07
03
b1111 $
#218
b0 '
b0 #
b11111111111111111111111111111110 (
b1110 ,
0.
0/
00
01
17
16
15
14
13
b1110 $
#220
b1 '
b1 #
b11111111111111111111111111111101 (
b1101 ,
11
07
b1101 $
#222
b10 '
b10 #
b11111111111111111111111111111100 (
b1100 ,
10
01
17
06
b1100 $
#224
b11 '
b11 #
b11111111111111111111111111111011 (
b1011 ,
11
07
b1011 $
#226
b100 '
b100 #
b11111111111111111111111111111010 (
b1010 ,
1/
00
01
17
16
05
b1010 $
#228
b101 '
b101 #
b11111111111111111111111111111001 (
b1001 ,
11
07
b1001 $
#230
b110 '
b110 #
b11111111111111111111111111111000 (
b1000 ,
10
01
17
06
b1000 $
#232
b111 '
b111 #
b11111111111111111111111111110111 (
b111 ,
11
07
b111 $
#233
1+
1%
#234
b1000 '
b11111111111111111111111111111111 &
b11111111111111111111111111111000 '
b1111 "
b1000 #
b111 (
1.
0/
00
01
b1111 -
17
16
15
04
#235
0+
0%
#236
b11111111111111111111111111111001 '
b1001 #
b110 (
b110 ,
11
07
b110 $
#238
b11111111111111111111111111111010 '
b1010 #
b101 (
b101 ,
10
01
17
06
b101 $
#240
b11111111111111111111111111111011 '
b1011 #
b100 (
b100 ,
11
07
b100 $
#242
b11111111111111111111111111111100 '
b1100 #
b11 (
b11 ,
1/
00
01
17
16
05
b11 $
#244
b11111111111111111111111111111101 '
b1101 #
b10 (
b10 ,
11
07
b10 $
#246
b11111111111111111111111111111110 '
b1110 #
b1 (
b1 ,
10
01
17
06
b1 $
#248
b11111111111111111111111111111111 '
b1111 #
b0 (
b0 ,
11
07
b0 $
#250
b0 '
b0 #
b11111111111111111111111111111111 (
b1111 ,
0.
0/
00
01
17
16
15
14
b1111 $
#252
b1 '
b1 #
b11111111111111111111111111111110 (
b1110 ,
11
07
b1110 $
#254
b10 '
b10 #
b11111111111111111111111111111101 (
b1101 ,
10
01
17
06
b1101 $
#256
b11 '
b11 #
b11111111111111111111111111111100 (
b1100 ,
11
07
b1100 $
#258
b100 '
b100 #
b11111111111111111111111111111011 (
b1011 ,
1/
00
01
17
16
05
b1011 $
#260
b101 '
b101 #
b11111111111111111111111111111010 (
b1010 ,
11
07
b1010 $
#262
b110 '
b110 #
b11111111111111111111111111111001 (
b1001 ,
10
01
17
06
b1001 $
#264
b111 '
b111 #
b11111111111111111111111111111000 (
b1000 ,
11
07
b1000 $
#266
b1000 '
b0 &
b11111111111111111111111111111000 '
b0 "
b1000 #
b1000 (
1.
0/
00
01
b0 -
17
16
15
04
03
#267
1+
1%
#268
b11111111111111111111111111111001 '
b1001 #
b111 (
b111 ,
11
07
b111 $
#269
0+
0%
#270
b11111111111111111111111111111010 '
b1010 #
b110 (
b110 ,
10
01
17
06
b110 $
#272
b11111111111111111111111111111011 '
b1011 #
b101 (
b101 ,
11
07
b101 $
#274
b11111111111111111111111111111100 '
b1100 #
b100 (
b100 ,
1/
00
01
17
16
05
b100 $
#276
b11111111111111111111111111111101 '
b1101 #
b11 (
b11 ,
11
07
b11 $
#278
b11111111111111111111111111111110 '
b1110 #
b10 (
b10 ,
10
01
17
06
b10 $
#280
b11111111111111111111111111111111 '
b1111 #
b1 (
b1 ,
11
07
b1 $
#282
b0 '
b0 #
b0 (
b0 ,
0.
0/
00
01
17
16
15
14
13
b0 $
#284
b1 '
b1 #
b11111111111111111111111111111111 (
b1111 ,
11
07
03
b1111 $
#286
b10 '
b10 #
b11111111111111111111111111111110 (
b1110 ,
10
01
17
06
b1110 $
#288
b11 '
b11 #
b11111111111111111111111111111101 (
b1101 ,
11
07
b1101 $
#290
b100 '
b100 #
b11111111111111111111111111111100 (
b1100 ,
1/
00
01
17
16
05
b1100 $
#292
b101 '
b101 #
b11111111111111111111111111111011 (
b1011 ,
11
07
b1011 $
#294
b110 '
b110 #
b11111111111111111111111111111010 (
b1010 ,
10
01
17
06
b1010 $
#296
b111 '
b111 #
b11111111111111111111111111111001 (
b1001 ,
11
07
b1001 $
#298
b1000 '
b1 &
b11111111111111111111111111111000 '
b1 "
b1000 #
b1001 (
1.
0/
00
01
b1 -
17
16
15
04
#299
1+
1%
#300
b11111111111111111111111111111001 '
b1001 #
b1000 (
b1000 ,
11
07
b1000 $
#302
b11111111111111111111111111111010 '
b1010 #
b111 (
b111 ,
10
01
17
06
b111 $
#303
0+
0%
#304
b11111111111111111111111111111011 '
b1011 #
b110 (
b110 ,
11
07
b110 $
#306
b11111111111111111111111111111100 '
b1100 #
b101 (
b101 ,
1/
00
01
17
16
05
b101 $
#308
b11111111111111111111111111111101 '
b1101 #
b100 (
b100 ,
11
07
b100 $
#310
b11111111111111111111111111111110 '
b1110 #
b11 (
b11 ,
10
01
17
06
b11 $
#312
b11111111111111111111111111111111 '
b1111 #
b10 (
b10 ,
11
07
b10 $
#314
b0 '
b0 #
b1 (
b1 ,
0.
0/
00
01
17
16
15
14
13
b1 $
#316
b1 '
b1 #
b0 (
b0 ,
11
07
b0 $
#318
b10 '
b10 #
b11111111111111111111111111111111 (
b1111 ,
10
01
17
06
03
b1111 $
#320
b11 '
b11 #
b11111111111111111111111111111110 (
b1110 ,
11
07
b1110 $
#322
b100 '
b100 #
b11111111111111111111111111111101 (
b1101 ,
1/
00
01
17
16
05
b1101 $
#324
b101 '
b101 #
b11111111111111111111111111111100 (
b1100 ,
11
07
b1100 $
#326
b110 '
b110 #
b11111111111111111111111111111011 (
b1011 ,
10
01
17
06
b1011 $
#328
b111 '
b111 #
b11111111111111111111111111111010 (
b1010 ,
11
07
b1010 $
#330
b1000 '
b10 &
b11111111111111111111111111111000 '
b10 "
b1000 #
b1010 (
1.
0/
00
01
b10 -
17
16
15
04
#331
1+
1%
#332
b11111111111111111111111111111001 '
b1001 #
b1001 (
b1001 ,
11
07
b1001 $
#334
b11111111111111111111111111111010 '
b1010 #
b1000 (
b1000 ,
10
01
17
06
b1000 $
#336
b11111111111111111111111111111011 '
b1011 #
b111 (
b111 ,
11
07
b111 $
#337
0+
0%
#338
b11111111111111111111111111111100 '
b1100 #
b110 (
b110 ,
1/
00
01
17
16
05
b110 $
#340
b11111111111111111111111111111101 '
b1101 #
b101 (
b101 ,
11
07
b101 $
#342
b11111111111111111111111111111110 '
b1110 #
b100 (
b100 ,
10
01
17
06
b100 $
#344
b11111111111111111111111111111111 '
b1111 #
b11 (
b11 ,
11
07
b11 $
#346
b0 '
b0 #
b10 (
b10 ,
0.
0/
00
01
17
16
15
14
13
b10 $
#348
b1 '
b1 #
b1 (
b1 ,
11
07
b1 $
#350
b10 '
b10 #
b0 (
b0 ,
10
01
17
06
b0 $
#352
b11 '
b11 #
b11111111111111111111111111111111 (
b1111 ,
11
07
03
b1111 $
#354
b100 '
b100 #
b11111111111111111111111111111110 (
b1110 ,
1/
00
01
17
16
05
b1110 $
#356
b101 '
b101 #
b11111111111111111111111111111101 (
b1101 ,
11
07
b1101 $
#358
b110 '
b110 #
b11111111111111111111111111111100 (
b1100 ,
10
01
17
06
b1100 $
#360
b111 '
b111 #
b11111111111111111111111111111011 (
b1011 ,
11
07
b1011 $
#362
b1000 '
b11 &
b11111111111111111111111111111000 '
b11 "
b1000 #
b1011 (
1.
0/
00
01
b11 -
17
16
15
04
#363
1+
1%
#364
b11111111111111111111111111111001 '
b1001 #
b1010 (
b1010 ,
11
07
b1010 $
#366
b11111111111111111111111111111010 '
b1010 #
b1001 (
b1001 ,
10
01
17
06
b1001 $
#368
b11111111111111111111111111111011 '
b1011 #
b1000 (
b1000 ,
11
07
b1000 $
#370
b11111111111111111111111111111100 '
b1100 #
b111 (
b111 ,
1/
00
01
17
16
05
b111 $
#371
0+
0%
#372
b11111111111111111111111111111101 '
b1101 #
b110 (
b110 ,
11
07
b110 $
#374
b11111111111111111111111111111110 '
b1110 #
b101 (
b101 ,
10
01
17
06
b101 $
#376
b11111111111111111111111111111111 '
b1111 #
b100 (
b100 ,
11
07
b100 $
#378
b0 '
b0 #
b11 (
b11 ,
0.
0/
00
01
17
16
15
14
13
b11 $
#380
b1 '
b1 #
b10 (
b10 ,
11
07
b10 $
#382
b10 '
b10 #
b1 (
b1 ,
10
01
17
06
b1 $
#384
b11 '
b11 #
b0 (
b0 ,
11
07
b0 $
#386
b100 '
b100 #
b11111111111111111111111111111111 (
b1111 ,
1/
00
01
17
16
05
03
b1111 $
#388
b101 '
b101 #
b11111111111111111111111111111110 (
b1110 ,
11
07
b1110 $
#390
b110 '
b110 #
b11111111111111111111111111111101 (
b1101 ,
10
01
17
06
b1101 $
#392
b111 '
b111 #
b11111111111111111111111111111100 (
b1100 ,
11
07
b1100 $
#394
b1000 '
b100 &
b11111111111111111111111111111000 '
b100 "
b1000 #
b1100 (
1.
0/
00
01
b100 -
17
16
15
04
#395
1+
1%
#396
b11111111111111111111111111111001 '
b1001 #
b1011 (
b1011 ,
11
07
b1011 $
#398
b11111111111111111111111111111010 '
b1010 #
b1010 (
b1010 ,
10
01
17
06
b1010 $
#400
b11111111111111111111111111111011 '
b1011 #
b1001 (
b1001 ,
11
07
b1001 $
#402
b11111111111111111111111111111100 '
b1100 #
b1000 (
b1000 ,
1/
00
01
17
16
05
b1000 $
#404
b11111111111111111111111111111101 '
b1101 #
b111 (
b111 ,
11
07
b111 $
#405
0+
0%
#406
b11111111111111111111111111111110 '
b1110 #
b110 (
b110 ,
10
01
17
06
b110 $
#408
b11111111111111111111111111111111 '
b1111 #
b101 (
b101 ,
11
07
b101 $
#410
b0 '
b0 #
b100 (
b100 ,
0.
0/
00
01
17
16
15
14
13
b100 $
#412
b1 '
b1 #
b11 (
b11 ,
11
07
b11 $
#414
b10 '
b10 #
b10 (
b10 ,
10
01
17
06
b10 $
#416
b11 '
b11 #
b1 (
b1 ,
11
07
b1 $
#418
b100 '
b100 #
b0 (
b0 ,
1/
00
01
17
16
05
b0 $
#420
b101 '
b101 #
b11111111111111111111111111111111 (
b1111 ,
11
07
03
b1111 $
#422
b110 '
b110 #
b11111111111111111111111111111110 (
b1110 ,
10
01
17
06
b1110 $
#424
b111 '
b111 #
b11111111111111111111111111111101 (
b1101 ,
11
07
b1101 $
#426
b1000 '
b101 &
b11111111111111111111111111111000 '
b101 "
b1000 #
b1101 (
1.
0/
00
01
b101 -
17
16
15
04
#427
1+
1%
#428
b11111111111111111111111111111001 '
b1001 #
b1100 (
b1100 ,
11
07
b1100 $
#430
b11111111111111111111111111111010 '
b1010 #
b1011 (
b1011 ,
10
01
17
06
b1011 $
#432
b11111111111111111111111111111011 '
b1011 #
b1010 (
b1010 ,
11
07
b1010 $
#434
b11111111111111111111111111111100 '
b1100 #
b1001 (
b1001 ,
1/
00
01
17
16
05
b1001 $
#436
b11111111111111111111111111111101 '
b1101 #
b1000 (
b1000 ,
11
07
b1000 $
#438
b11111111111111111111111111111110 '
b1110 #
b111 (
b111 ,
10
01
17
06
b111 $
#439
0+
0%
#440
b11111111111111111111111111111111 '
b1111 #
b110 (
b110 ,
11
07
b110 $
#442
b0 '
b0 #
b101 (
b101 ,
0.
0/
00
01
17
16
15
14
13
b101 $
#444
b1 '
b1 #
b100 (
b100 ,
11
07
b100 $
#446
b10 '
b10 #
b11 (
b11 ,
10
01
17
06
b11 $
#448
b11 '
b11 #
b10 (
b10 ,
11
07
b10 $
#450
b100 '
b100 #
b1 (
b1 ,
1/
00
01
17
16
05
b1 $
#452
b101 '
b101 #
b0 (
b0 ,
11
07
b0 $
#454
b110 '
b110 #
b11111111111111111111111111111111 (
b1111 ,
10
01
17
06
03
b1111 $
#456
b111 '
b111 #
b11111111111111111111111111111110 (
b1110 ,
11
07
b1110 $
#458
b1000 '
b110 &
b11111111111111111111111111111000 '
b110 "
b1000 #
b1110 (
1.
0/
00
01
b110 -
17
16
15
04
#459
1+
1%
#460
b11111111111111111111111111111001 '
b1001 #
b1101 (
b1101 ,
11
07
b1101 $
#462
b11111111111111111111111111111010 '
b1010 #
b1100 (
b1100 ,
10
01
17
06
b1100 $
#464
b11111111111111111111111111111011 '
b1011 #
b1011 (
b1011 ,
11
07
b1011 $
#466
b11111111111111111111111111111100 '
b1100 #
b1010 (
b1010 ,
1/
00
01
17
16
05
b1010 $
#468
b11111111111111111111111111111101 '
b1101 #
b1001 (
b1001 ,
11
07
b1001 $
#470
b11111111111111111111111111111110 '
b1110 #
b1000 (
b1000 ,
10
01
17
06
b1000 $
#472
b11111111111111111111111111111111 '
b1111 #
b111 (
b111 ,
11
07
b111 $
#473
0+
0%
#474
b0 '
b0 #
b110 (
b110 ,
0.
0/
00
01
17
16
15
14
13
b110 $
#476
b1 '
b1 #
b101 (
b101 ,
11
07
b101 $
#478
b10 '
b10 #
b100 (
b100 ,
10
01
17
06
b100 $
#480
b11 '
b11 #
b11 (
b11 ,
11
07
b11 $
#482
b100 '
b100 #
b10 (
b10 ,
1/
00
01
17
16
05
b10 $
#484
b101 '
b101 #
b1 (
b1 ,
11
07
b1 $
#486
b110 '
b110 #
b0 (
b0 ,
10
01
17
06
b0 $
#488
b111 '
b111 #
b11111111111111111111111111111111 (
b1111 ,
11
07
03
b1111 $
#490
b1000 '
b111 &
b11111111111111111111111111111000 '
b111 "
b1000 #
b1111 (
1.
0/
00
01
b111 -
17
16
15
04
#491
1+
1%
#492
b11111111111111111111111111111001 '
b1001 #
b1110 (
b1110 ,
11
07
b1110 $
#494
b11111111111111111111111111111010 '
b1010 #
b1101 (
b1101 ,
10
01
17
06
b1101 $
#496
b11111111111111111111111111111011 '
b1011 #
b1100 (
b1100 ,
11
07
b1100 $
#498
b11111111111111111111111111111100 '
b1100 #
b1011 (
b1011 ,
1/
00
01
17
16
05
b1011 $
#500
b11111111111111111111111111111101 '
b1101 #
b1010 (
b1010 ,
11
07
b1010 $
#502
b11111111111111111111111111111110 '
b1110 #
b1001 (
b1001 ,
10
01
17
06
b1001 $
#504
b11111111111111111111111111111111 '
b1111 #
b1000 (
b1000 ,
11
07
b1000 $
#506
b0 '
b0 #
b111 (
b111 ,
0.
0/
00
01
17
16
15
14
13
b111 $
#507
0+
0%
#508
b1 '
b1 #
b110 (
b110 ,
11
07
b110 $
#510
b10 '
b10 #
b101 (
b101 ,
10
01
17
06
b101 $
#512
b11 '
b11 #
b100 (
b100 ,
11
07
b100 $
#514
b100 '
b100 #
b11 (
b11 ,
1/
00
01
17
16
05
b11 $
#516
b101 '
b101 #
b10 (
b10 ,
11
07
b10 $
#518
b110 '
b110 #
b1 (
b1 ,
10
01
17
06
b1 $
#520
b111 '
b111 #
b0 (
b0 ,
11
07
b0 $
