ex7/sat_count.v
module sat_count(clk, reset, branch, taken, prediction);
   parameter N=2;
   input clk, reset, branch, taken;
   output prediction;

   reg 	  prediction;
   reg 	  [1:0] state; 

   localparam ZERO=2'b00, ONE=2'b01, TWO=2'b10, SAT=2'b11;

   always @(posedge clk)
   begin
		if (reset)
			state <= ZERO;
		else if (branch == 0)
			state <= state;
		else // if reset == 0 and branch == 1
			case (state)
			ZERO:		if(taken ==1)
							state <= ONE;
						else 
							state <= ZERO;
			ONE:		if(taken ==1)
							state <= TWO;
						else
							state <= ZERO;
			TWO:		if(taken ==1)
							state <= SAT;
						else
							state <= ONE;
			SAT:		if(taken ==1)
							state <= SAT;
						else
							state <= TWO;				
			default:	state <= ZERO;
	  endcase
    end

   always @(state) 
   begin
		if (state >= TWO)
			prediction = 1;
		else
			prediction = 0;
	end
 
endmodule

ex7/sat_count_tb.v
module main;
   reg clk, reset, taken, branch;
   wire prediction;

   sat_count sat_count(clk, reset, branch, taken, prediction);
   
   integer test;
   
   always #5 clk = ~clk;

	initial
    begin
	$monitor("time=%d: reset=%b, branch=%b, taken=%b -> prediction is: %b\n", $time, reset, branch, taken, prediction);
	$dumpfile("waves.vcd");
	$dumpvars;
		clk = 0;
        reset = 1; branch = 0; taken = 1;
		#10
				branch = 1; taken = 1;
		#10
				branch = 1; taken = 1;
		#10
				branch = 1; taken = 1;
				
		if (prediction == 0) // reset = 1 - ZERO state - should be prediction == 0
			test = 1; // test passed
		else
			test = 0;
		#10
		
		reset = 0; branch = 1; taken = 1;
		#10
				branch = 1; taken = 1;
		#10
				branch = 1; taken = 1;
		#10
				
		if (prediction == 1) // taken=1 for 3 cycles - should be in SAT state and prediction=1
			test = test + 1; // test passed
		else
			test = 0;
		#10
		
		branch = 0; taken = 0;
		#10
				taken = 0;
		#10
				taken = 0;
		if (prediction == 1) // branch = 0 - should stay in SAT state and prediction=1
			test = test + 1; // test passed
		else
			test = 0;
			
	if (test == 3) // sat_count is correct if all the prediction were as expected
		$display("PASSED ALL TESTS");
	$finish;
	end
endmodule

ex7/waves.vcd
$date
    Nov 13, 2021  20:13:11
$end
$version
    TOOL:	ncsim(64)	15.20-s085
$end
$timescale
    1 ns
$end

$scope module main $end
$var reg       1 !    clk  $end
$var reg       1 "    reset  $end
$var reg       1 #    taken  $end
$var reg       1 $    branch  $end
$var wire      1 %    prediction  $end
$var integer  32 &    test  $end

$scope module sat_count $end
$var parameter 32 '    N  $end
$var wire      1 (    clk  $end
$var wire      1 )    reset  $end
$var wire      1 *    branch  $end
$var wire      1 +    taken  $end
$var reg       1 ,    prediction  $end
$var reg       2 -    state [1:0] $end
$var parameter  2 .    ZERO  $end
$var parameter  2 /    ONE  $end
$var parameter  2 0    TWO  $end
$var parameter  2 1    SAT  $end
$upscope $end

$upscope $end

$enddefinitions $end
$dumpvars
b11 1
b10 0
b1 /
b0 .
b10 '
0!
1"
1#
0$
x%
bx &
0(
1)
0*
1+
x,
bx -
$end
#5
1!
1(
b0 -
0,
0%
#10
1$
0!
0(
1*
#15
1!
1(
#20
0!
0(
#25
1!
1(
#30
b1 &
0!
0(
#35
1!
1(
#40
0"
0!
0(
0)
#45
1!
1(
b1 -
#50
0!
0(
#55
1!
1(
b10 -
1,
1%
#60
0!
0(
#65
1!
1(
b11 -
#70
b10 &
0!
0(
#75
1!
1(
#80
0$
0#
0!
0(
0+
0*
#85
1!
1(
#90
0!
0(
#95
1!
1(
#100
b11 &
